tests/__init__.py
tests/test_database.py
tests/test_models.py
tests/test_mqtt_client.py
tests/test_mqtt_config.py
tests/test_service.py
tests/test_state_checker.py
tests/test_tracker.py
workpulse/__init__.py
workpulse/_version.py
workpulse/cli.py
workpulse/database.py
workpulse/homeassistant.py
workpulse/models.py
workpulse/mqtt_client.py
workpulse/mqtt_config.py
workpulse/service.py
workpulse/state_checker.py
workpulse/tracker.py
workpulse-0.4.0.dist-info/licenses/LICENSE
workpulse-0.4.0.dist-info/METADATA
workpulse-0.4.0.dist-info/WHEEL
workpulse-0.4.0.dist-info/entry_points.txt
workpulse-0.4.0.dist-info/top_level.txt
workpulse-0.4.0.dist-info/RECORD
